{
  "project": "积分计算器",
  "version": "V1.0",
  "status": "DRAFT",
  "current_node": "BRAINSTORM",
  "node_list": [
    {
      "node": "ROUTER",
      "status": "CONFIRM",
      "output": {}
    },
    {
      "node": "BRAINSTORM",
      "status": "DRAFT",
      "output": {
        "path": "./analysis_process/brainstorm.md"
      }
    },
    {
      "node": "CLARIFY",
      "status": "PENDING",
      "output": {
        "path": "./analysis_process/clarify.md"
      }
    },
    {
      "node": "ANALYSIS",
      "status": "PENDING",
      "output": {
        "path": "./output/V1.0/PRD_V1.0.md"
      }
    },
    {
      "node": "DRAWUSERSTORY",
      "status": "PENDING",
      "output": {
        "page_key": "user_story",
        "page_id": ""
      }
    },
    {
      "node": "DETAIL",
      "status": "PENDING",
      "output": {
        "page_key": "detail_design",
        "page_id": ""
      }
    },
    {
      "node": "GENPROTOTYPE",
      "status": "PENDING",
      "output": {
        "page_key": "prototype",
        "page_id": ""
      }
    },
    {
      "node": "GENHTML",
      "status": "PENDING",
      "output": {
        "path": "./output/V1.0/prototype/"
      }
    }
  ],
  "penpot": {
    "pages": {}
  }
}
